LICENSE.txt
MANIFEST.in
README.md
setup.py
hapiplotserver/__init__.py
hapiplotserver/app.py
hapiplotserver/config.py
hapiplotserver/hapiplotserver
hapiplotserver/hapiplotserver.py
hapiplotserver/log.py
hapiplotserver/plot.py
hapiplotserver/viviz.py
hapiplotserver.egg-info/PKG-INFO
hapiplotserver.egg-info/SOURCES.txt
hapiplotserver.egg-info/dependency_links.txt
hapiplotserver.egg-info/requires.txt
hapiplotserver.egg-info/top_level.txt
hapiplotserver/html/favicon.ico
hapiplotserver/html/index.html
hapiplotserver/test/__init__.py
hapiplotserver/test/test_commandline.py
hapiplotserver/test/test_hapiplotserver.py