Metadata-Version: 2.1
Name: hapiplotserver
Version: 0.1.4
Summary: Heliophysics API
Home-page: http://pypi.python.org/pypi/hapiplotserver/
Author: Bob Weigel
Author-email: rweigel@gmu.edu
License: LICENSE.txt
Platform: UNKNOWN
License-File: LICENSE.txt
